Metadata-Version: 2.1
Name: FairAlerts
Version: 1.0.0
Summary: A third party alert system interface.
Home-page: https://github.com/chazzcoin/fairalerts
Author: ChazzCoin
Author-email: chazzcoin@gmail.com
License: BSD 2-clause
Platform: UNKNOWN
Classifier: Development Status :: 1 - Planning
Classifier: Intended Audience :: Science/Research
Classifier: License :: OSI Approved :: BSD License
Classifier: Operating System :: POSIX :: Linux
Classifier: Programming Language :: Python :: 3.8
Classifier: Programming Language :: Python :: 3.9
